CHANGES.txt
README.txt
TODO.txt
buildout.cfg
setup.py
bootstrap/bootstrap.py
src/megrok/__init__.py
src/megrok.trails.egg-info/PKG-INFO
src/megrok.trails.egg-info/SOURCES.txt
src/megrok.trails.egg-info/dependency_links.txt
src/megrok.trails.egg-info/entry_points.txt
src/megrok.trails.egg-info/namespace_packages.txt
src/megrok.trails.egg-info/not-zip-safe
src/megrok.trails.egg-info/requires.txt
src/megrok.trails.egg-info/top_level.txt
src/megrok/trails/__init__.py
src/megrok/trails/components.py
src/megrok/trails/ftesting.zcml
src/megrok/trails/ftests/__init__.py
src/megrok/trails/ftests/test_trails_functional.py
src/megrok/trails/ftests/traversal/__init__.py
src/megrok/trails/ftests/traversal/traversal.py
src/megrok/trails/ftests/url/__init__.py
src/megrok/trails/ftests/url/url.py