Metadata-Version: 1.0
Name: megrok.trails
Version: 1.0
Summary: URL patterns for Grok applications
Home-page: UNKNOWN
Author: Brandon Craig Rhodes
Author-email: brandon@rhodesmill.org
License: ZPL
Keywords: grok megrok trail trails url
Platform: UNKNOWN
Classifier: Development Status :: 5 - Production/Stable
Classifier: Environment :: Web Environment
Classifier: Framework :: Zope3
Classifier: Intended Audience :: Developers
Classifier: License :: OSI Approved :: Zope Public License
Classifier: Operating System :: OS Independent
Classifier: Programming Language :: Python
Classifier: Topic :: Internet :: WWW/HTTP
Classifier: Topic :: Software Development :: Libraries
